{
  "tactic_bow": "{\n  \"DataVersion\": 4903,\n  \"id\": \"minecraft:bow\",\n  \"count\": 1,\n  \"components\": {\n    \"minecraft:lore\": \"[{color:\\\"gray\\\",text:\\\"\\\"},{color:\\\"gray\\\",italic:0b,text:\\\"Un arma prevalente que posee un poder no\\\"},{color:\\\"gray\\\",italic:0b,text:\\\"autorizado por las entidades superiores.\\\"},{color:\\\"gray\\\",text:\\\"\\\"},{color:\\\"light_purple\\\",extra:[{color:\\\"dark_purple\\\",text:\\\"misiones\\\"},\\\" en Tezzlar III.\\\"],italic:0b,text:\\\"Obtenido por completar \\\"}]\",\n    \"minecraft:enchantments\": \"{\\\"minecraft:infinity\\\":1,\\\"minecraft:mending\\\":1}\",\n    \"minecraft:custom_name\": \"{extra:[{color:\\\"gray\\\",obfuscated:1b,text:\\\";;\\\"},\\\" \\\",{color:\\\"dark_red\\\",extra:[{color:\\\"yellow\\\",text:\\\"➹\\\"},\\\" Arco Táctico \\\",{color:\\\"yellow\\\",text:\\\"🏹\\\"}],text:\\\"\\\"},\\\" \\\",{color:\\\"gray\\\",obfuscated:1b,text:\\\";;\\\"}],italic:0b,shadow_color:1073698133,text:\\\"\\\"}\",\n    \"minecraft:custom_data\": \"{PublicBukkitValues:{\\\"tezzlar3:custom_item_id\\\":\\\"tactic_bow\\\"}}\"\n  },\n  \"schema_version\": 1\n}",
  "premium_iron_helmet": "{\n  \"DataVersion\": 4903,\n  \"id\": \"minecraft:iron_helmet\",\n  \"count\": 1,\n  \"components\": {\n    \"minecraft:attribute_modifiers\": \"[{amount:5.0d,id:\\\"minecraft:b6e49f44-eb80-4a18-a240-e374cd97c7d4\\\",operation:\\\"add_value\\\",slot:\\\"head\\\",type:\\\"minecraft:armor\\\"},{amount:4.0d,id:\\\"minecraft:83ed2e71-6e62-41cc-ad74-1e65805c42c5\\\",operation:\\\"add_value\\\",slot:\\\"head\\\",type:\\\"minecraft:armor_toughness\\\"},{amount:1.0d,id:\\\"minecraft:92207ca4-ab03-4b8b-976b-c34fdbd0ebf9\\\",operation:\\\"add_value\\\",slot:\\\"head\\\",type:\\\"minecraft:max_health\\\"}]\",\n    \"minecraft:lore\": \"[{italic:0b,text:\\\"\\\"},{color:\\\"dark_gray\\\",italic:0b,text:\\\"Muestra de respeto a aquellos quiénes\\\"},{color:\\\"dark_gray\\\",italic:0b,text:\\\"forjaron un sistema de seguridad sólido.\\\"},{italic:0b,text:\\\"\\\"},{color:\\\"light_purple\\\",extra:[{color:\\\"dark_purple\\\",text:\\\"misiones\\\"},\\\" en Tezzlar III.\\\"],italic:0b,text:\\\"Obtenido por completar \\\"}]\",\n    \"minecraft:max_damage\": \"611\",\n    \"minecraft:enchantments\": \"{\\\"minecraft:fire_protection\\\":4,\\\"minecraft:protection\\\":4}\",\n    \"minecraft:custom_name\": \"{extra:[{color:\\\"#4380F0\\\",text:\\\"➥\\\"},{extra:[{color:\\\"#B3B3B3\\\",text:\\\"C\\\"},{color:\\\"#BABABA\\\",text:\\\"a\\\"},{color:\\\"#C1C1C1\\\",text:\\\"s\\\"},{color:\\\"#C8C8C8\\\",text:\\\"c\\\"},{color:\\\"#CFCFCF\\\",text:\\\"o\\\"},{color:\\\"#D6D6D6\\\",text:\\\" \\\"},{color:\\\"#DCDCDC\\\",text:\\\"d\\\"},{color:\\\"#E3E3E3\\\",text:\\\"e\\\"},{color:\\\"#EAEAEA\\\",text:\\\" \\\"},{color:\\\"#F1F1F1\\\",text:\\\"H\\\"},{color:\\\"#F8F8F8\\\",text:\\\"i\\\"},{color:\\\"white\\\",text:\\\"e\\\"},{color:\\\"#F8F8F8\\\",text:\\\"r\\\"},{color:\\\"#F1F1F1\\\",text:\\\"r\\\"},{color:\\\"#EAEAEA\\\",text:\\\"o\\\"},{color:\\\"#E3E3E3\\\",text:\\\" \\\"},{color:\\\"#DCDCDC\\\",text:\\\"P\\\"},{color:\\\"#D6D6D6\\\",text:\\\"r\\\"},{color:\\\"#CFCFCF\\\",text:\\\"é\\\"},{color:\\\"#C8C8C8\\\",text:\\\"m\\\"},{color:\\\"#C1C1C1\\\",text:\\\"i\\\"},{color:\\\"#BABABA\\\",text:\\\"u\\\"},{color:\\\"#B3B3B3\\\",text:\\\"m\\\"}],text:\\\" \\\"},\\\" \\\",{color:\\\"gray\\\",obfuscated:1b,text:\\\";;\\\"}],italic:0b,shadow_color:-16098214,text:\\\"\\\"}\",\n    \"minecraft:custom_data\": \"{PublicBukkitValues:{\\\"tezzlar3:custom_item_id\\\":\\\"premium_iron_helmet\\\"}}\",\n    \"minecraft:damage\": \"1\"\n  },\n  \"schema_version\": 1\n}",
  "premium_iron_chestplate": "{\n  \"DataVersion\": 4903,\n  \"id\": \"minecraft:iron_chestplate\",\n  \"count\": 1,\n  \"components\": {\n    \"minecraft:attribute_modifiers\": \"[{amount:9.0d,id:\\\"minecraft:c1000000-0000-0000-0000-000000000001\\\",operation:\\\"add_value\\\",slot:\\\"chest\\\",type:\\\"minecraft:armor\\\"},{amount:4.0d,id:\\\"minecraft:c1000000-0000-0000-0000-000000000002\\\",operation:\\\"add_value\\\",slot:\\\"chest\\\",type:\\\"minecraft:armor_toughness\\\"},{amount:1.0d,id:\\\"minecraft:c1000000-0000-0000-0000-000000000003\\\",operation:\\\"add_value\\\",slot:\\\"chest\\\",type:\\\"minecraft:max_health\\\"}]\",\n    \"minecraft:lore\": \"[{italic:0b,text:\\\"\\\"},{color:\\\"dark_gray\\\",italic:0b,text:\\\"Muestra de respeto a aquellos quiénes\\\"},{color:\\\"dark_gray\\\",italic:0b,text:\\\"forjaron un sistema de seguridad sólido.\\\"},{italic:0b,text:\\\"\\\"},{color:\\\"light_purple\\\",extra:[{color:\\\"dark_purple\\\",text:\\\"misiones\\\"},\\\" en Tezzlar III.\\\"],italic:0b,text:\\\"Obtenido por completar \\\"}]\",\n    \"minecraft:max_damage\": \"888\",\n    \"minecraft:enchantments\": \"{\\\"minecraft:projectile_protection\\\":4,\\\"minecraft:protection\\\":4}\",\n    \"minecraft:custom_name\": \"{extra:[{color:\\\"#4380F0\\\",text:\\\"➥\\\"},{extra:[{color:\\\"#B3B3B3\\\",text:\\\"P\\\"},{color:\\\"#BABABA\\\",text:\\\"e\\\"},{color:\\\"#C1C1C1\\\",text:\\\"t\\\"},{color:\\\"#C8C8C8\\\",text:\\\"o\\\"},{color:\\\"#CFCFCF\\\",text:\\\" \\\"},{color:\\\"#D6D6D6\\\",text:\\\"d\\\"},{color:\\\"#DCDCDC\\\",text:\\\"e\\\"},{color:\\\"#E3E3E3\\\",text:\\\" \\\"},{color:\\\"#EAEAEA\\\",text:\\\"H\\\"},{color:\\\"#F1F1F1\\\",text:\\\"i\\\"},{color:\\\"#F8F8F8\\\",text:\\\"e\\\"},{color:\\\"white\\\",text:\\\"r\\\"},{color:\\\"#F8F8F8\\\",text:\\\"r\\\"},{color:\\\"#F1F1F1\\\",text:\\\"o\\\"},{color:\\\"#EAEAEA\\\",text:\\\" \\\"},{color:\\\"#E3E3E3\\\",text:\\\"P\\\"},{color:\\\"#DCDCDC\\\",text:\\\"r\\\"},{color:\\\"#D6D6D6\\\",text:\\\"é\\\"},{color:\\\"#CFCFCF\\\",text:\\\"m\\\"},{color:\\\"#C8C8C8\\\",text:\\\"i\\\"},{color:\\\"#C1C1C1\\\",text:\\\"u\\\"},{color:\\\"#BABABA\\\",text:\\\"m\\\"}],text:\\\" \\\"},\\\" \\\",{color:\\\"gray\\\",obfuscated:1b,text:\\\";;\\\"}],italic:0b,shadow_color:-16098214,text:\\\"\\\"}\",\n    \"minecraft:custom_data\": \"{PublicBukkitValues:{\\\"tezzlar3:custom_item_id\\\":\\\"premium_iron_chestplate\\\"}}\",\n    \"minecraft:damage\": \"1\"\n  },\n  \"schema_version\": 1\n}",
  "premium_iron_leggings": "{\n  \"DataVersion\": 4903,\n  \"id\": \"minecraft:iron_leggings\",\n  \"count\": 1,\n  \"components\": {\n    \"minecraft:attribute_modifiers\": \"[{amount:7.0d,id:\\\"minecraft:c2000000-0000-0000-0000-000000000001\\\",operation:\\\"add_value\\\",slot:\\\"legs\\\",type:\\\"minecraft:armor\\\"},{amount:4.0d,id:\\\"minecraft:c2000000-0000-0000-0000-000000000002\\\",operation:\\\"add_value\\\",slot:\\\"legs\\\",type:\\\"minecraft:armor_toughness\\\"},{amount:1.0d,id:\\\"minecraft:c2000000-0000-0000-0000-000000000003\\\",operation:\\\"add_value\\\",slot:\\\"legs\\\",type:\\\"minecraft:max_health\\\"}]\",\n    \"minecraft:lore\": \"[{italic:0b,text:\\\"\\\"},{color:\\\"dark_gray\\\",italic:0b,text:\\\"Muestra de respeto a aquellos quiénes\\\"},{color:\\\"dark_gray\\\",italic:0b,text:\\\"forjaron un sistema de seguridad sólido.\\\"},{italic:0b,text:\\\"\\\"},{color:\\\"light_purple\\\",extra:[{color:\\\"dark_purple\\\",text:\\\"misiones\\\"},\\\" en Tezzlar III.\\\"],italic:0b,text:\\\"Obtenido por completar \\\"}]\",\n    \"minecraft:max_damage\": \"833\",\n    \"minecraft:enchantments\": \"{\\\"minecraft:blast_protection\\\":4,\\\"minecraft:protection\\\":4}\",\n    \"minecraft:custom_name\": \"{extra:[{color:\\\"#4380F0\\\",text:\\\"➥\\\"},{extra:[{color:\\\"#A9A9A9\\\",text:\\\"P\\\"},{color:\\\"#AFAFAF\\\",text:\\\"e\\\"},{color:\\\"#B5B5B5\\\",text:\\\"r\\\"},{color:\\\"#BBBBBB\\\",text:\\\"n\\\"},{color:\\\"#C1C1C1\\\",text:\\\"e\\\"},{color:\\\"#C7C7C7\\\",text:\\\"r\\\"},{color:\\\"#CDCDCD\\\",text:\\\"a\\\"},{color:\\\"#D3D3D3\\\",text:\\\"s\\\"},{color:\\\"#D9D9D9\\\",text:\\\" \\\"},{color:\\\"#DFDFDF\\\",text:\\\"d\\\"},{color:\\\"#E5E5E5\\\",text:\\\"e\\\"},{color:\\\"#EBEBEB\\\",text:\\\" \\\"},{color:\\\"#F1F1F1\\\",text:\\\"H\\\"},{color:\\\"#F7F7F7\\\",text:\\\"i\\\"},{color:\\\"white\\\",text:\\\"e\\\"},{color:\\\"#F7F7F7\\\",text:\\\"r\\\"},{color:\\\"#F1F1F1\\\",text:\\\"r\\\"},{color:\\\"#EBEBEB\\\",text:\\\"o\\\"},{color:\\\"#E5E5E5\\\",text:\\\" \\\"},{color:\\\"#DFDFDF\\\",text:\\\"P\\\"},{color:\\\"#D9D9D9\\\",text:\\\"r\\\"},{color:\\\"#D3D3D3\\\",text:\\\"é\\\"},{color:\\\"#CDCDCD\\\",text:\\\"m\\\"},{color:\\\"#C7C7C7\\\",text:\\\"i\\\"},{color:\\\"#C1C1C1\\\",text:\\\"u\\\"},{color:\\\"#BBBBBB\\\",text:\\\"m\\\"}],text:\\\" \\\"},\\\" \\\",{color:\\\"gray\\\",obfuscated:1b,text:\\\";;\\\"}],italic:0b,shadow_color:-16098214,text:\\\"\\\"}\",\n    \"minecraft:custom_data\": \"{PublicBukkitValues:{\\\"tezzlar3:custom_item_id\\\":\\\"premium_iron_leggings\\\"}}\",\n    \"minecraft:damage\": \"1\"\n  },\n  \"schema_version\": 1\n}",
  "premium_iron_boots": "{\n  \"DataVersion\": 4903,\n  \"id\": \"minecraft:iron_boots\",\n  \"count\": 1,\n  \"components\": {\n    \"minecraft:attribute_modifiers\": \"[{amount:5.0d,id:\\\"minecraft:c3000000-0000-0000-0000-000000000001\\\",operation:\\\"add_value\\\",slot:\\\"feet\\\",type:\\\"minecraft:armor\\\"},{amount:4.0d,id:\\\"minecraft:c3000000-0000-0000-0000-000000000002\\\",operation:\\\"add_value\\\",slot:\\\"feet\\\",type:\\\"minecraft:armor_toughness\\\"},{amount:1.0d,id:\\\"minecraft:c3000000-0000-0000-0000-000000000003\\\",operation:\\\"add_value\\\",slot:\\\"feet\\\",type:\\\"minecraft:max_health\\\"}]\",\n    \"minecraft:lore\": \"[{italic:0b,text:\\\"\\\"},{color:\\\"dark_gray\\\",italic:0b,text:\\\"Muestra de respeto a aquellos quiénes\\\"},{color:\\\"dark_gray\\\",italic:0b,text:\\\"forjaron un sistema de seguridad sólido.\\\"},{italic:0b,text:\\\"\\\"},{color:\\\"light_purple\\\",extra:[{color:\\\"dark_purple\\\",text:\\\"misiones\\\"},\\\" en Tezzlar III.\\\"],italic:0b,text:\\\"Obtenido por completar \\\"}]\",\n    \"minecraft:max_damage\": \"722\",\n    \"minecraft:enchantments\": \"{\\\"minecraft:feather_falling\\\":5,\\\"minecraft:protection\\\":4}\",\n    \"minecraft:custom_name\": \"{extra:[{color:\\\"#4380F0\\\",text:\\\"➥\\\"},{extra:[{color:\\\"#B3B3B3\\\",text:\\\"B\\\"},{color:\\\"#BABABA\\\",text:\\\"o\\\"},{color:\\\"#C1C1C1\\\",text:\\\"t\\\"},{color:\\\"#C8C8C8\\\",text:\\\"a\\\"},{color:\\\"#CFCFCF\\\",text:\\\"s\\\"},{color:\\\"#D6D6D6\\\",text:\\\" \\\"},{color:\\\"#DCDCDC\\\",text:\\\"d\\\"},{color:\\\"#E3E3E3\\\",text:\\\"e\\\"},{color:\\\"#EAEAEA\\\",text:\\\" \\\"},{color:\\\"#F1F1F1\\\",text:\\\"H\\\"},{color:\\\"#F8F8F8\\\",text:\\\"i\\\"},{color:\\\"white\\\",text:\\\"e\\\"},{color:\\\"#F8F8F8\\\",text:\\\"r\\\"},{color:\\\"#F1F1F1\\\",text:\\\"r\\\"},{color:\\\"#EAEAEA\\\",text:\\\"o\\\"},{color:\\\"#E3E3E3\\\",text:\\\" \\\"},{color:\\\"#DCDCDC\\\",text:\\\"P\\\"},{color:\\\"#D6D6D6\\\",text:\\\"r\\\"},{color:\\\"#CFCFCF\\\",text:\\\"é\\\"},{color:\\\"#C8C8C8\\\",text:\\\"m\\\"},{color:\\\"#C1C1C1\\\",text:\\\"i\\\"},{color:\\\"#BABABA\\\",text:\\\"u\\\"},{color:\\\"#B3B3B3\\\",text:\\\"m\\\"}],text:\\\" \\\"},\\\" \\\",{color:\\\"gray\\\",obfuscated:1b,text:\\\";;\\\"}],italic:0b,shadow_color:-16098214,text:\\\"\\\"}\",\n    \"minecraft:custom_data\": \"{PublicBukkitValues:{\\\"tezzlar3:custom_item_id\\\":\\\"premium_iron_boots\\\"}}\",\n    \"minecraft:damage\": \"1\"\n  },\n  \"schema_version\": 1\n}\n}
